{"summitCode": "W7M/FN-110", "name": "Elk Mountain", "shortCode": "FN-110", "altM": 2388, "altFt": 7835, "gridRef1": "-113.4445", "gridRef2": "48.3066", "notes": "", "validFrom": "0001-01-01T00:00:00", "validTo": "0001-01-01T00:00:00", "activationCount": null, "myActivations": null, "activationDate": null, "myChases": null, "activationCall": null, "longitude": -113.4445, "latitude": 48.3066, "locator": "DN38gh", "points": 6, "regionCode": "FN", "regionName": "MT - North Flathead County", "associationCode": "W7M", "associationName": "USA - Montana"}